basico/__init__.py
basico/basico.py
basico/core/__init__.py
basico/core/mod_env.py
basico/core/mod_log.py
basico/core/mod_srv.py
basico/core/mod_wdg.py
basico/core/mod_win.py
basico/data/desktop/basico.desktop
basico/data/icons/basico-about.svg
basico/data/icons/basico-add.svg
basico/data/icons/basico-annotation-priority-high.svg
basico/data/icons/basico-annotation-priority-low.svg
basico/data/icons/basico-annotation-priority-normal.svg
basico/data/icons/basico-annotation-type-bookmark.svg
basico/data/icons/basico-annotation-type-email.svg
basico/data/icons/basico-annotation-type-fixme.svg
basico/data/icons/basico-annotation-type-incident.svg
basico/data/icons/basico-annotation-type-meeting.svg
basico/data/icons/basico-annotation-type-note.svg
basico/data/icons/basico-annotation-type-procedure.svg
basico/data/icons/basico-annotation-type-snippet.svg
basico/data/icons/basico-annotation-type-template.svg
basico/data/icons/basico-annotation-type-todo.svg
basico/data/icons/basico-annotation.svg
basico/data/icons/basico-archived.svg
basico/data/icons/basico-backup-ms-excel.png
basico/data/icons/basico-backup-ms-excel.svg
basico/data/icons/basico-backup-restore.svg
basico/data/icons/basico-backup-text-csv.svg
basico/data/icons/basico-backup-text-generic.svg
basico/data/icons/basico-backup-text-json.svg
basico/data/icons/basico-backup.svg
basico/data/icons/basico-bookmark-off.svg
basico/data/icons/basico-bookmark-on.svg
basico/data/icons/basico-bookmarks.svg
basico/data/icons/basico-browse.svg
basico/data/icons/basico-category.svg
basico/data/icons/basico-chart.svg
basico/data/icons/basico-check-accept.svg
basico/data/icons/basico-check-cancel.svg
basico/data/icons/basico-chronologic.svg
basico/data/icons/basico-clipboard.svg
basico/data/icons/basico-collection.svg
basico/data/icons/basico-comments.svg
basico/data/icons/basico-component.svg
basico/data/icons/basico-dashboard.svg
basico/data/icons/basico-delete.svg
basico/data/icons/basico-description.svg
basico-0.3.dist-info/AUTHORS
basico-0.3.dist-info/LICENSE
basico-0.3.dist-info/METADATA
basico-0.3.dist-info/WHEEL
basico-0.3.dist-info/entry_points.txt
basico-0.3.dist-info/top_level.txt
basico-0.3.dist-info/RECORD
