Metadata-Version: 2.1
Name: basico
Version: 0.3
Summary: SAP Notes Manager for SAP Consultants
Home-page: http://subversion.t00mlabs.net/basico
Author: Tomás Vírseda
Author-email: tomasvirseda@gmail.com
License: GPLv3
Download-URL: http://t00mlabs.net/downloads/basico-0.3.tar.gz
Platform: any
Classifier: Development Status :: 3 - Alpha
Classifier: Environment :: X11 Applications :: Gnome
Classifier: Environment :: X11 Applications :: GTK
Classifier: Intended Audience :: Information Technology
Classifier: Intended Audience :: Other Audience
Classifier: Intended Audience :: System Administrators
Classifier: License :: OSI Approved :: GNU General Public License v3 or later (GPLv3+)
Classifier: Natural Language :: English
Classifier: Operating System :: Microsoft :: Windows
Classifier: Operating System :: POSIX :: Linux
Classifier: Programming Language :: Python :: 3
Classifier: Topic :: Database :: Front-Ends
Classifier: Topic :: System :: Systems Administration
Classifier: Topic :: Utilities
Requires-Dist: python-dateutil
Requires-Dist: selenium
Requires-Dist: feedparser
Requires-Dist: requests
Requires-Dist: openpyxl
